<?xml version="1.0"?>
<ns2:test-suite xmlns="" xmlns:ns2="urn:model.allure.qatools.yandex.ru" start="1566838915190" stop="1566839900003">
  <name>Registro Imigrante</name>
  <title>Registro Imigrante</title>
  <test-cases>
    <test-case start="1566838915197" stop="1566838959645" status="passed">
      <name>Gerar Requerimento de Registro do Imigrante</name>
      <title>Gerar Requerimento de Registro do Imigrante</title>
      <steps>
        <step start="1566838917781" stop="1566838917783" status="passed">
          <name>Quando realizar o procedimento de "Registro" de Imigrante na Internet</name>
          <title>Quando realizar o procedimento de "Registro" de Imigrante na Internet</title>
          <attachments/>
        </step>
        <step start="1566838917784" stop="1566838930718" status="passed">
          <name>E preencho Dados Pessoais do requerimento e clico em Proximo</name>
          <title>E preencho Dados Pessoais do requerimento e clico em Proximo</title>
          <attachments/>
        </step>
        <step start="1566838930718" stop="1566838934857" status="passed">
          <name>E preencho Dados do Registro do requerimento e clico em Proximo</name>
          <title>E preencho Dados do Registro do requerimento e clico em Proximo</title>
          <attachments/>
        </step>
        <step start="1566838934857" stop="1566838949397" status="passed">
          <name>E preencho Dados do Endereco do requerimento e clico em Proximo</name>
          <title>E preencho Dados do Endereco do requerimento e clico em Proximo</title>
          <attachments/>
        </step>
        <step start="1566838949398" stop="1566838959362" status="passed">
          <name>E preencho Dados da Declaracao e clico em Salvar</name>
          <title>E preencho Dados da Declaracao e clico em Salvar</title>
          <attachments/>
        </step>
        <step start="1566838959362" stop="1566838959363" status="passed">
          <name>Entao visualizo a Impressao da Solicitacao referente</name>
          <title>Entao visualizo a Impressao da Solicitacao referente</title>
          <attachments/>
        </step>
      </steps>
      <attachments>
        <attachment source="118fcfdd9d0b56a2ffeae29bafb32385d69525ce74e07d36ae925bace0aef76c-attachment.png" title="Clique aqui para ver o print da tela" size="63015" type="image/png"/>
      </attachments>
      <labels>
        <label name="severity" value="normal"/>
        <label name="thread" value="21750940"/>
        <label name="host" value="DESKTOP-PVI2LJO"/>
        <label name="feature" value="Registro Imigrante"/>
        <label name="story" value="Gerar Requerimento de Registro do Imigrante"/>
      </labels>
      <parameters/>
    </test-case>
    <test-case start="1566838959650" stop="1566838961652" status="passed">
      <name>Verificar Protocolo de Registro do Imigrante em Aberto na Internet</name>
      <title>Verificar Protocolo de Registro do Imigrante em Aberto na Internet</title>
      <steps>
        <step start="1566838960758" stop="1566838960758" status="passed">
          <name>Quando realizar o procedimento de "Verificacao_de_Protocolo" de Imigrante na Internet</name>
          <title>Quando realizar o procedimento de "Verificacao_de_Protocolo" de Imigrante na Internet</title>
          <attachments/>
        </step>
        <step start="1566838960759" stop="1566838961313" status="passed">
          <name>E preencho os Dados de "Registro" do requerimento para "Verificacao_de_Protocolo" e clico em Verificar</name>
          <title>E preencho os Dados de "Registro" do requerimento para "Verificacao_de_Protocolo" e clico em Verificar</title>
          <attachments/>
        </step>
        <step start="1566838961313" stop="1566838961315" status="passed">
          <name>Entao eu visualizo a Verificacao do Protocolo referente</name>
          <title>Entao eu visualizo a Verificacao do Protocolo referente</title>
          <attachments/>
        </step>
      </steps>
      <attachments>
        <attachment source="0c2957ee539aae72b99ac43c1ab90378ce620a83dd97304122caeb14b0a64564-attachment.png" title="Clique aqui para ver o print da tela" size="24113" type="image/png"/>
      </attachments>
      <labels>
        <label name="severity" value="normal"/>
        <label name="thread" value="21750940"/>
        <label name="host" value="DESKTOP-PVI2LJO"/>
        <label name="feature" value="Registro Imigrante"/>
        <label name="story" value="Verificar Protocolo de Registro do Imigrante em Aberto na Internet"/>
      </labels>
      <parameters/>
    </test-case>
    <test-case start="1566838961656" stop="1566838964845" status="passed">
      <name>Andamento do Requerimento de Registro do Imigrante em Aberto na Internet</name>
      <title>Andamento do Requerimento de Registro do Imigrante em Aberto na Internet</title>
      <steps>
        <step start="1566838962803" stop="1566838962803" status="passed">
          <name>Quando realizar o procedimento de "Andamento_do_Requerimento" de Imigrante na Internet</name>
          <title>Quando realizar o procedimento de "Andamento_do_Requerimento" de Imigrante na Internet</title>
          <attachments/>
        </step>
        <step start="1566838962803" stop="1566838964529" status="passed">
          <name>E preencho os Dados de "Registro" do requerimento para "Andamento_do_Requerimento" e clico em Pesquisar</name>
          <title>E preencho os Dados de "Registro" do requerimento para "Andamento_do_Requerimento" e clico em Pesquisar</title>
          <attachments/>
        </step>
        <step start="1566838964529" stop="1566838964530" status="passed">
          <name>Entao eu visualizo o andamento do requerimento "Em Aberto"</name>
          <title>Entao eu visualizo o andamento do requerimento "Em Aberto"</title>
          <attachments/>
        </step>
      </steps>
      <attachments>
        <attachment source="a1dbfa6a95c228cd4b1bc9326f48cb30765e8303e5a6b68180162a53f641bb4a-attachment.png" title="Clique aqui para ver o print da tela" size="97039" type="image/png"/>
      </attachments>
      <labels>
        <label name="severity" value="normal"/>
        <label name="thread" value="21750940"/>
        <label name="host" value="DESKTOP-PVI2LJO"/>
        <label name="feature" value="Registro Imigrante"/>
        <label name="story" value="Andamento do Requerimento de Registro do Imigrante em Aberto na Internet"/>
      </labels>
      <parameters/>
    </test-case>
    <test-case start="1566838964850" stop="1566839035636" status="passed">
      <name>Alterar Tipos de Solicitacoes de Registro do Imigrante em Aberto na Intranet</name>
      <title>Alterar Tipos de Solicitacoes de Registro do Imigrante em Aberto na Intranet</title>
      <steps>
        <step start="1566838972639" stop="1566838972639" status="passed">
          <name>Quando processar atendimento de "Registro" no menu "Processar_Atendimento" na Intranet</name>
          <title>Quando processar atendimento de "Registro" no menu "Processar_Atendimento" na Intranet</title>
          <attachments/>
        </step>
        <step start="1566838972639" stop="1566838976530" status="passed">
          <name>E preencher as informacoes para Pesquisar Solicitacao de "Registro" na Situacao "Em Aberto"</name>
          <title>E preencher as informacoes para Pesquisar Solicitacao de "Registro" na Situacao "Em Aberto"</title>
          <attachments/>
        </step>
        <step start="1566838976530" stop="1566839035188" status="passed">
          <name>E clico para Alterar o Tipo de Solicitacao de "Registro"</name>
          <title>E clico para Alterar o Tipo de Solicitacao de "Registro"</title>
          <attachments/>
        </step>
      </steps>
      <attachments>
        <attachment source="68576f631eebcdb7f5f1dd0922e37effd485dad02a60ab6c05039e2000fbdd63-attachment.png" title="Clique aqui para ver o print da tela" size="9477" type="image/png"/>
      </attachments>
      <labels>
        <label name="severity" value="normal"/>
        <label name="thread" value="21750940"/>
        <label name="host" value="DESKTOP-PVI2LJO"/>
        <label name="feature" value="Registro Imigrante"/>
        <label name="story" value="Alterar Tipos de Solicitacoes de Registro do Imigrante em Aberto na Intranet"/>
      </labels>
      <parameters/>
    </test-case>
    <test-case start="1566839035658" stop="1566839044031" status="passed">
      <name>Situacao do Requerimento de Registro do Imigrante em Aberto na Intranet</name>
      <title>Situacao do Requerimento de Registro do Imigrante em Aberto na Intranet</title>
      <steps>
        <step start="1566839041946" stop="1566839041946" status="passed">
          <name>Quando solicitar Situacao do Requerimento de "Registro" no menu "Situacao_do_Requerimento" na Intranet</name>
          <title>Quando solicitar Situacao do Requerimento de "Registro" no menu "Situacao_do_Requerimento" na Intranet</title>
          <attachments/>
        </step>
        <step start="1566839041946" stop="1566839043697" status="passed">
          <name>E preencho o numero do Requerimento para verificar a Situacao do Requerimento</name>
          <title>E preencho o numero do Requerimento para verificar a Situacao do Requerimento</title>
          <attachments/>
        </step>
        <step start="1566839043697" stop="1566839043698" status="passed">
          <name>Entao eu visualizo a situacao do Requerimento "Em Aberto"</name>
          <title>Entao eu visualizo a situacao do Requerimento "Em Aberto"</title>
          <attachments/>
        </step>
      </steps>
      <attachments>
        <attachment source="7e85e8e0fde6546d442cfadd597c5d8a13ff44113fff90f17ecb2792c76798e1-attachment.png" title="Clique aqui para ver o print da tela" size="108665" type="image/png"/>
      </attachments>
      <labels>
        <label name="severity" value="normal"/>
        <label name="thread" value="21750940"/>
        <label name="host" value="DESKTOP-PVI2LJO"/>
        <label name="feature" value="Registro Imigrante"/>
        <label name="story" value="Situacao do Requerimento de Registro do Imigrante em Aberto na Intranet"/>
      </labels>
      <parameters/>
    </test-case>
    <test-case start="1566839044038" stop="1566839284431" status="passed">
      <name>Processar Atendimento de Registro do Imigrante em Aberto na Intranet</name>
      <title>Processar Atendimento de Registro do Imigrante em Aberto na Intranet</title>
      <steps>
        <step start="1566839050541" stop="1566839050541" status="passed">
          <name>Quando processar atendimento de "Registro" no menu "Processar_Atendimento" na Intranet</name>
          <title>Quando processar atendimento de "Registro" no menu "Processar_Atendimento" na Intranet</title>
          <attachments/>
        </step>
        <step start="1566839050541" stop="1566839054240" status="passed">
          <name>E preencher as informacoes para Pesquisar Solicitacao de "Registro" na Situacao "Em Aberto"</name>
          <title>E preencher as informacoes para Pesquisar Solicitacao de "Registro" na Situacao "Em Aberto"</title>
          <attachments/>
        </step>
        <step start="1566839054240" stop="1566839245280" status="passed">
          <name>E preencho Dados Pessoais e clico em Proximo</name>
          <title>E preencho Dados Pessoais e clico em Proximo</title>
          <attachments/>
        </step>
        <step start="1566839245281" stop="1566839252301" status="passed">
          <name>E preencho Dados do Registro e clico em Proximo</name>
          <title>E preencho Dados do Registro e clico em Proximo</title>
          <attachments/>
        </step>
        <step start="1566839252301" stop="1566839256702" status="passed">
          <name>E preencho Dados do Endereco e clico em Proximo</name>
          <title>E preencho Dados do Endereco e clico em Proximo</title>
          <attachments/>
        </step>
        <step start="1566839256702" stop="1566839271345" status="passed">
          <name>E preencho Dados de Documentos e clico em Proximo</name>
          <title>E preencho Dados de Documentos e clico em Proximo</title>
          <attachments/>
        </step>
        <step start="1566839271345" stop="1566839277637" status="passed">
          <name>E preencho Dados do Resultado da Pesquisa e clico em Proximo</name>
          <title>E preencho Dados do Resultado da Pesquisa e clico em Proximo</title>
          <attachments/>
        </step>
        <step start="1566839277637" stop="1566839284042" status="passed">
          <name>E visualizo Dados da Previa da Carteira e clico em "Concluir"</name>
          <title>E visualizo Dados da Previa da Carteira e clico em "Concluir"</title>
          <attachments/>
        </step>
        <step start="1566839284042" stop="1566839284043" status="passed">
          <name>Entao verifico o requerimento referente "Em Processamento"</name>
          <title>Entao verifico o requerimento referente "Em Processamento"</title>
          <attachments/>
        </step>
      </steps>
      <attachments>
        <attachment source="53b32403e9ca28c3b1ea121bb543e6c1c481dcaf03559e84617a47809a303c87-attachment.png" title="Clique aqui para ver o print da tela" size="62727" type="image/png"/>
      </attachments>
      <labels>
        <label name="severity" value="normal"/>
        <label name="thread" value="21750940"/>
        <label name="host" value="DESKTOP-PVI2LJO"/>
        <label name="feature" value="Registro Imigrante"/>
        <label name="story" value="Processar Atendimento de Registro do Imigrante em Aberto na Intranet"/>
      </labels>
      <parameters/>
    </test-case>
    <test-case start="1566839284440" stop="1566839293187" status="passed">
      <name>Situacao do Requerimento de Registro do Imigrante que estava em aberto em Processamento na Intranet</name>
      <title>Situacao do Requerimento de Registro do Imigrante que estava em aberto em Processamento na Intranet</title>
      <steps>
        <step start="1566839290966" stop="1566839290966" status="passed">
          <name>Quando solicitar Situacao do Requerimento de "Registro" no menu "Situacao_do_Requerimento" na Intranet</name>
          <title>Quando solicitar Situacao do Requerimento de "Registro" no menu "Situacao_do_Requerimento" na Intranet</title>
          <attachments/>
        </step>
        <step start="1566839290966" stop="1566839292793" status="passed">
          <name>E preencho o numero do Requerimento para verificar a Situacao do Requerimento</name>
          <title>E preencho o numero do Requerimento para verificar a Situacao do Requerimento</title>
          <attachments/>
        </step>
        <step start="1566839292793" stop="1566839292794" status="passed">
          <name>Entao eu visualizo a situacao do Requerimento "Em Processamento"</name>
          <title>Entao eu visualizo a situacao do Requerimento "Em Processamento"</title>
          <attachments/>
        </step>
      </steps>
      <attachments>
        <attachment source="bcca7d9834425be4d5f98a6b560e8369976b3141b4b3ef80f648f694bb3dff4d-attachment.png" title="Clique aqui para ver o print da tela" size="108442" type="image/png"/>
      </attachments>
      <labels>
        <label name="severity" value="normal"/>
        <label name="thread" value="21750940"/>
        <label name="host" value="DESKTOP-PVI2LJO"/>
        <label name="feature" value="Registro Imigrante"/>
        <label name="story" value="Situacao do Requerimento de Registro do Imigrante que estava em aberto em Processamento na Intranet"/>
      </labels>
      <parameters/>
    </test-case>
    <test-case start="1566839293191" stop="1566839440082" status="passed">
      <name>Gerar Requerimento de Registro do Imigrante para situacao em Analise</name>
      <title>Gerar Requerimento de Registro do Imigrante para situacao em Analise</title>
      <steps>
        <step start="1566839294691" stop="1566839294691" status="passed">
          <name>Quando realizar o procedimento de "Registro" de Imigrante na Internet</name>
          <title>Quando realizar o procedimento de "Registro" de Imigrante na Internet</title>
          <attachments/>
        </step>
        <step start="1566839294692" stop="1566839299695" status="passed">
          <name>E preencho Dados Pessoais do requerimento e clico em Proximo</name>
          <title>E preencho Dados Pessoais do requerimento e clico em Proximo</title>
          <attachments/>
        </step>
        <step start="1566839299696" stop="1566839303989" status="passed">
          <name>E preencho Dados do Registro do requerimento e clico em Proximo</name>
          <title>E preencho Dados do Registro do requerimento e clico em Proximo</title>
          <attachments/>
        </step>
        <step start="1566839303989" stop="1566839318633" status="passed">
          <name>E preencho Dados do Endereco do requerimento e clico em Proximo</name>
          <title>E preencho Dados do Endereco do requerimento e clico em Proximo</title>
          <attachments/>
        </step>
        <step start="1566839318633" stop="1566839360680" status="passed">
          <name>E preencho Dados da Declaracao e clico em Salvar</name>
          <title>E preencho Dados da Declaracao e clico em Salvar</title>
          <attachments/>
        </step>
        <step start="1566839360680" stop="1566839367356" status="passed">
          <name>E processar atendimento de "Registro" no menu "Processar_Atendimento" na Intranet</name>
          <title>E processar atendimento de "Registro" no menu "Processar_Atendimento" na Intranet</title>
          <attachments/>
        </step>
        <step start="1566839367356" stop="1566839371219" status="passed">
          <name>E preencher as informacoes para Pesquisar Solicitacao de "Registro" na Situacao "Em Aberto"</name>
          <title>E preencher as informacoes para Pesquisar Solicitacao de "Registro" na Situacao "Em Aberto"</title>
          <attachments/>
        </step>
        <step start="1566839371219" stop="1566839402104" status="passed">
          <name>E preencho Dados Pessoais e clico em Proximo</name>
          <title>E preencho Dados Pessoais e clico em Proximo</title>
          <attachments/>
        </step>
        <step start="1566839402104" stop="1566839408509" status="passed">
          <name>E preencho Dados do Registro e clico em Proximo</name>
          <title>E preencho Dados do Registro e clico em Proximo</title>
          <attachments/>
        </step>
        <step start="1566839408509" stop="1566839412888" status="passed">
          <name>E preencho Dados do Endereco e clico em Proximo</name>
          <title>E preencho Dados do Endereco e clico em Proximo</title>
          <attachments/>
        </step>
        <step start="1566839412889" stop="1566839427641" status="passed">
          <name>E preencho Dados de Documentos e clico em Proximo</name>
          <title>E preencho Dados de Documentos e clico em Proximo</title>
          <attachments/>
        </step>
        <step start="1566839427641" stop="1566839429116" status="passed">
          <name>E clico no icone Home para abortar a solicitacao e pesquiso o requerimento novamente</name>
          <title>E clico no icone Home para abortar a solicitacao e pesquiso o requerimento novamente</title>
          <attachments/>
        </step>
        <step start="1566839429116" stop="1566839435850" status="passed">
          <name>E processar atendimento de "Registro" no menu "Processar_Atendimento" na Intranet</name>
          <title>E processar atendimento de "Registro" no menu "Processar_Atendimento" na Intranet</title>
          <attachments/>
        </step>
        <step start="1566839435851" stop="1566839439716" status="passed">
          <name>E preencher as informacoes para Pesquisar Solicitacao de "Registro" na Situacao "Em an&#xE1;lise"</name>
          <title>E preencher as informacoes para Pesquisar Solicitacao de "Registro" na Situacao "Em an&#xE1;lise"</title>
          <attachments/>
        </step>
        <step start="1566839439716" stop="1566839439720" status="passed">
          <name>Entao verifico o requerimento referente "Em an&#xE1;lise"</name>
          <title>Entao verifico o requerimento referente "Em an&#xE1;lise"</title>
          <attachments/>
        </step>
      </steps>
      <attachments>
        <attachment source="875b28a1a27b4636e82bd6c42889c144eea4b247bc3aca68e9c9d275396be853-attachment.png" title="Clique aqui para ver o print da tela" size="4990" type="image/png"/>
      </attachments>
      <labels>
        <label name="severity" value="normal"/>
        <label name="thread" value="21750940"/>
        <label name="host" value="DESKTOP-PVI2LJO"/>
        <label name="feature" value="Registro Imigrante"/>
        <label name="story" value="Gerar Requerimento de Registro do Imigrante para situacao em Analise"/>
      </labels>
      <parameters/>
    </test-case>
    <test-case start="1566839440086" stop="1566839441978" status="passed">
      <name>Verificar Protocolo de Registro do Imigrante em Analise na Internet</name>
      <title>Verificar Protocolo de Registro do Imigrante em Analise na Internet</title>
      <steps>
        <step start="1566839441148" stop="1566839441148" status="passed">
          <name>Quando realizar o procedimento de "Verificacao_de_Protocolo" de Imigrante na Internet</name>
          <title>Quando realizar o procedimento de "Verificacao_de_Protocolo" de Imigrante na Internet</title>
          <attachments/>
        </step>
        <step start="1566839441148" stop="1566839441695" status="passed">
          <name>E preencho os Dados de "Registro" do requerimento para "Verificacao_de_Protocolo" e clico em Verificar</name>
          <title>E preencho os Dados de "Registro" do requerimento para "Verificacao_de_Protocolo" e clico em Verificar</title>
          <attachments/>
        </step>
        <step start="1566839441695" stop="1566839441697" status="passed">
          <name>Entao eu visualizo a Verificacao do Protocolo referente</name>
          <title>Entao eu visualizo a Verificacao do Protocolo referente</title>
          <attachments/>
        </step>
      </steps>
      <attachments>
        <attachment source="1ba9acf8be2e2f97253e5e96b428c51d8b784725a3dac478386f4cd8e25a4854-attachment.png" title="Clique aqui para ver o print da tela" size="19578" type="image/png"/>
      </attachments>
      <labels>
        <label name="severity" value="normal"/>
        <label name="thread" value="21750940"/>
        <label name="host" value="DESKTOP-PVI2LJO"/>
        <label name="feature" value="Registro Imigrante"/>
        <label name="story" value="Verificar Protocolo de Registro do Imigrante em Analise na Internet"/>
      </labels>
      <parameters/>
    </test-case>
    <test-case start="1566839441982" stop="1566839445564" status="passed">
      <name>Andamento do Requerimento de Registro do Imigrante em Analise na Internet</name>
      <title>Andamento do Requerimento de Registro do Imigrante em Analise na Internet</title>
      <steps>
        <step start="1566839443295" stop="1566839443295" status="passed">
          <name>Quando realizar o procedimento de "Andamento_do_Requerimento" de Imigrante na Internet</name>
          <title>Quando realizar o procedimento de "Andamento_do_Requerimento" de Imigrante na Internet</title>
          <attachments/>
        </step>
        <step start="1566839443295" stop="1566839445279" status="passed">
          <name>E preencho os Dados de "Registro" do requerimento para "Andamento_do_Requerimento" e clico em Pesquisar</name>
          <title>E preencho os Dados de "Registro" do requerimento para "Andamento_do_Requerimento" e clico em Pesquisar</title>
          <attachments/>
        </step>
        <step start="1566839445279" stop="1566839445280" status="passed">
          <name>Entao eu visualizo o andamento do requerimento "Em an&#xE1;lise"</name>
          <title>Entao eu visualizo o andamento do requerimento "Em an&#xE1;lise"</title>
          <attachments/>
        </step>
      </steps>
      <attachments>
        <attachment source="58cdd58a272a3ac9e2715bdf0658c1c08af5affd421220602994b058364fd1bb-attachment.png" title="Clique aqui para ver o print da tela" size="60747" type="image/png"/>
      </attachments>
      <labels>
        <label name="severity" value="normal"/>
        <label name="thread" value="21750940"/>
        <label name="host" value="DESKTOP-PVI2LJO"/>
        <label name="feature" value="Registro Imigrante"/>
        <label name="story" value="Andamento do Requerimento de Registro do Imigrante em Analise na Internet"/>
      </labels>
      <parameters/>
    </test-case>
    <test-case start="1566839445569" stop="1566839516566" status="passed">
      <name>Alterar Tipos de Solicitacoes de Registro do Imigrante em Analise na Intranet</name>
      <title>Alterar Tipos de Solicitacoes de Registro do Imigrante em Analise na Intranet</title>
      <steps>
        <step start="1566839452206" stop="1566839452206" status="passed">
          <name>Quando processar atendimento de "Registro" no menu "Processar_Atendimento" na Intranet</name>
          <title>Quando processar atendimento de "Registro" no menu "Processar_Atendimento" na Intranet</title>
          <attachments/>
        </step>
        <step start="1566839452206" stop="1566839456297" status="passed">
          <name>E preencher as informacoes para Pesquisar Solicitacao de "Registro" na Situacao "Em an&#xE1;lise"</name>
          <title>E preencher as informacoes para Pesquisar Solicitacao de "Registro" na Situacao "Em an&#xE1;lise"</title>
          <attachments/>
        </step>
        <step start="1566839456297" stop="1566839516177" status="passed">
          <name>E clico para Alterar o Tipo de Solicitacao de "Registro"</name>
          <title>E clico para Alterar o Tipo de Solicitacao de "Registro"</title>
          <attachments/>
        </step>
      </steps>
      <attachments>
        <attachment source="875b28a1a27b4636e82bd6c42889c144eea4b247bc3aca68e9c9d275396be853-attachment.png" title="Clique aqui para ver o print da tela" size="4990" type="image/png"/>
      </attachments>
      <labels>
        <label name="severity" value="normal"/>
        <label name="thread" value="21750940"/>
        <label name="host" value="DESKTOP-PVI2LJO"/>
        <label name="feature" value="Registro Imigrante"/>
        <label name="story" value="Alterar Tipos de Solicitacoes de Registro do Imigrante em Analise na Intranet"/>
      </labels>
      <parameters/>
    </test-case>
    <test-case start="1566839516585" stop="1566839525377" status="passed">
      <name>Situacao do Requerimento de Registro do Imigrante em Analise na Intranet</name>
      <title>Situacao do Requerimento de Registro do Imigrante em Analise na Intranet</title>
      <steps>
        <step start="1566839523013" stop="1566839523013" status="passed">
          <name>Quando solicitar Situacao do Requerimento de "Registro" no menu "Situacao_do_Requerimento" na Intranet</name>
          <title>Quando solicitar Situacao do Requerimento de "Registro" no menu "Situacao_do_Requerimento" na Intranet</title>
          <attachments/>
        </step>
        <step start="1566839523013" stop="1566839525089" status="passed">
          <name>E preencho o numero do Requerimento para verificar a Situacao do Requerimento</name>
          <title>E preencho o numero do Requerimento para verificar a Situacao do Requerimento</title>
          <attachments/>
        </step>
        <step start="1566839525089" stop="1566839525090" status="passed">
          <name>Entao eu visualizo a situacao do Requerimento "Em an&#xE1;lise"</name>
          <title>Entao eu visualizo a situacao do Requerimento "Em an&#xE1;lise"</title>
          <attachments/>
        </step>
      </steps>
      <attachments>
        <attachment source="aeb94a7a634f4d327a92d2189a7614888ff91c82cf3c1dc69f2609cea1112889-attachment.png" title="Clique aqui para ver o print da tela" size="69491" type="image/png"/>
      </attachments>
      <labels>
        <label name="severity" value="normal"/>
        <label name="thread" value="21750940"/>
        <label name="host" value="DESKTOP-PVI2LJO"/>
        <label name="feature" value="Registro Imigrante"/>
        <label name="story" value="Situacao do Requerimento de Registro do Imigrante em Analise na Intranet"/>
      </labels>
      <parameters/>
    </test-case>
    <test-case start="1566839525384" stop="1566839624770" status="passed">
      <name>Processar Atendimento de Registro do Imigrante em Analise na Intranet</name>
      <title>Processar Atendimento de Registro do Imigrante em Analise na Intranet</title>
      <steps>
        <step start="1566839531912" stop="1566839531912" status="passed">
          <name>Quando processar atendimento de "Registro" no menu "Processar_Atendimento" na Intranet</name>
          <title>Quando processar atendimento de "Registro" no menu "Processar_Atendimento" na Intranet</title>
          <attachments/>
        </step>
        <step start="1566839531912" stop="1566839535687" status="passed">
          <name>E preencher as informacoes para Pesquisar Solicitacao de "Registro" na Situacao "Em an&#xE1;lise"</name>
          <title>E preencher as informacoes para Pesquisar Solicitacao de "Registro" na Situacao "Em an&#xE1;lise"</title>
          <attachments/>
        </step>
        <step start="1566839535687" stop="1566839591371" status="passed">
          <name>E preencho Dados Pessoais e clico em Proximo</name>
          <title>E preencho Dados Pessoais e clico em Proximo</title>
          <attachments/>
        </step>
        <step start="1566839591371" stop="1566839596767" status="passed">
          <name>E preencho Dados do Registro e clico em Proximo</name>
          <title>E preencho Dados do Registro e clico em Proximo</title>
          <attachments/>
        </step>
        <step start="1566839596767" stop="1566839601167" status="passed">
          <name>E preencho Dados do Endereco e clico em Proximo</name>
          <title>E preencho Dados do Endereco e clico em Proximo</title>
          <attachments/>
        </step>
        <step start="1566839601167" stop="1566839612422" status="passed">
          <name>E preencho Dados de Documentos e clico em Proximo</name>
          <title>E preencho Dados de Documentos e clico em Proximo</title>
          <attachments/>
        </step>
        <step start="1566839612422" stop="1566839618514" status="passed">
          <name>E preencho Dados do Resultado da Pesquisa e clico em Proximo</name>
          <title>E preencho Dados do Resultado da Pesquisa e clico em Proximo</title>
          <attachments/>
        </step>
        <step start="1566839618514" stop="1566839624439" status="passed">
          <name>E visualizo Dados da Previa da Carteira e clico em "Concluir"</name>
          <title>E visualizo Dados da Previa da Carteira e clico em "Concluir"</title>
          <attachments/>
        </step>
        <step start="1566839624439" stop="1566839624441" status="passed">
          <name>Entao verifico o requerimento referente "Em Processamento"</name>
          <title>Entao verifico o requerimento referente "Em Processamento"</title>
          <attachments/>
        </step>
      </steps>
      <attachments>
        <attachment source="087eaf0d9e27d9715b051bab1bbd209ffaa86a841365bdff1e71da096ce3c967-attachment.png" title="Clique aqui para ver o print da tela" size="56023" type="image/png"/>
      </attachments>
      <labels>
        <label name="severity" value="normal"/>
        <label name="thread" value="21750940"/>
        <label name="host" value="DESKTOP-PVI2LJO"/>
        <label name="feature" value="Registro Imigrante"/>
        <label name="story" value="Processar Atendimento de Registro do Imigrante em Analise na Intranet"/>
      </labels>
      <parameters/>
    </test-case>
    <test-case start="1566839624775" stop="1566839633599" status="passed">
      <name>Situacao do Requerimento de Registro do Imigrante que estava em analise em Processamento na Intranet</name>
      <title>Situacao do Requerimento de Registro do Imigrante que estava em analise em Processamento na Intranet</title>
      <steps>
        <step start="1566839631319" stop="1566839631319" status="passed">
          <name>Quando solicitar Situacao do Requerimento de "Registro" no menu "Situacao_do_Requerimento" na Intranet</name>
          <title>Quando solicitar Situacao do Requerimento de "Registro" no menu "Situacao_do_Requerimento" na Intranet</title>
          <attachments/>
        </step>
        <step start="1566839631320" stop="1566839633299" status="passed">
          <name>E preencho o numero do Requerimento para verificar a Situacao do Requerimento</name>
          <title>E preencho o numero do Requerimento para verificar a Situacao do Requerimento</title>
          <attachments/>
        </step>
        <step start="1566839633299" stop="1566839633300" status="passed">
          <name>Entao eu visualizo a situacao do Requerimento "Em Processamento"</name>
          <title>Entao eu visualizo a situacao do Requerimento "Em Processamento"</title>
          <attachments/>
        </step>
      </steps>
      <attachments>
        <attachment source="8a7485b4e2798d4f0366735da509a7a68d4c1d9418dc3ff465e3b79fd65ac46a-attachment.png" title="Clique aqui para ver o print da tela" size="69486" type="image/png"/>
      </attachments>
      <labels>
        <label name="severity" value="normal"/>
        <label name="thread" value="21750940"/>
        <label name="host" value="DESKTOP-PVI2LJO"/>
        <label name="feature" value="Registro Imigrante"/>
        <label name="story" value="Situacao do Requerimento de Registro do Imigrante que estava em analise em Processamento na Intranet"/>
      </labels>
      <parameters/>
    </test-case>
    <test-case start="1566839633603" stop="1566839748989" status="passed">
      <name>Gerar Requerimento de Registro do Imigrante para situacao em Suspenso</name>
      <title>Gerar Requerimento de Registro do Imigrante para situacao em Suspenso</title>
      <steps>
        <step start="1566839635023" stop="1566839635023" status="passed">
          <name>Quando realizar o procedimento de "Registro" de Imigrante na Internet</name>
          <title>Quando realizar o procedimento de "Registro" de Imigrante na Internet</title>
          <attachments/>
        </step>
        <step start="1566839635023" stop="1566839639997" status="passed">
          <name>E preencho Dados Pessoais do requerimento e clico em Proximo</name>
          <title>E preencho Dados Pessoais do requerimento e clico em Proximo</title>
          <attachments/>
        </step>
        <step start="1566839639997" stop="1566839644226" status="passed">
          <name>E preencho Dados do Registro do requerimento e clico em Proximo</name>
          <title>E preencho Dados do Registro do requerimento e clico em Proximo</title>
          <attachments/>
        </step>
        <step start="1566839644226" stop="1566839658809" status="passed">
          <name>E preencho Dados do Endereco do requerimento e clico em Proximo</name>
          <title>E preencho Dados do Endereco do requerimento e clico em Proximo</title>
          <attachments/>
        </step>
        <step start="1566839658809" stop="1566839676440" status="passed">
          <name>E preencho Dados da Declaracao e clico em Salvar</name>
          <title>E preencho Dados da Declaracao e clico em Salvar</title>
          <attachments/>
        </step>
        <step start="1566839676440" stop="1566839683040" status="passed">
          <name>E processar atendimento de "Registro" no menu "Processar_Atendimento" na Intranet</name>
          <title>E processar atendimento de "Registro" no menu "Processar_Atendimento" na Intranet</title>
          <attachments/>
        </step>
        <step start="1566839683040" stop="1566839686740" status="passed">
          <name>E preencher as informacoes para Pesquisar Solicitacao de "Registro" na Situacao "Em Aberto"</name>
          <title>E preencher as informacoes para Pesquisar Solicitacao de "Registro" na Situacao "Em Aberto"</title>
          <attachments/>
        </step>
        <step start="1566839686740" stop="1566839703701" status="passed">
          <name>E preencho Dados Pessoais e clico em Proximo</name>
          <title>E preencho Dados Pessoais e clico em Proximo</title>
          <attachments/>
        </step>
        <step start="1566839703701" stop="1566839709939" status="passed">
          <name>E preencho Dados do Registro e clico em Proximo</name>
          <title>E preencho Dados do Registro e clico em Proximo</title>
          <attachments/>
        </step>
        <step start="1566839709940" stop="1566839714411" status="passed">
          <name>E preencho Dados do Endereco e clico em Proximo</name>
          <title>E preencho Dados do Endereco e clico em Proximo</title>
          <attachments/>
        </step>
        <step start="1566839714411" stop="1566839728834" status="passed">
          <name>E preencho Dados de Documentos e clico em Proximo</name>
          <title>E preencho Dados de Documentos e clico em Proximo</title>
          <attachments/>
        </step>
        <step start="1566839728834" stop="1566839734801" status="passed">
          <name>E preencho Dados do Resultado da Pesquisa e clico em Proximo</name>
          <title>E preencho Dados do Resultado da Pesquisa e clico em Proximo</title>
          <attachments/>
        </step>
        <step start="1566839734801" stop="1566839738179" status="passed">
          <name>E visualizo Dados da Previa da Carteira e clico em "Suspender"</name>
          <title>E visualizo Dados da Previa da Carteira e clico em "Suspender"</title>
          <attachments/>
        </step>
        <step start="1566839738179" stop="1566839744664" status="passed">
          <name>E processar atendimento de "Registro" no menu "Processar_Atendimento" na Intranet</name>
          <title>E processar atendimento de "Registro" no menu "Processar_Atendimento" na Intranet</title>
          <attachments/>
        </step>
        <step start="1566839744664" stop="1566839748592" status="passed">
          <name>E preencher as informacoes para Pesquisar Solicitacao de "Registro" na Situacao "Suspenso"</name>
          <title>E preencher as informacoes para Pesquisar Solicitacao de "Registro" na Situacao "Suspenso"</title>
          <attachments/>
        </step>
        <step start="1566839748592" stop="1566839748598" status="passed">
          <name>Entao verifico o requerimento referente "Suspenso"</name>
          <title>Entao verifico o requerimento referente "Suspenso"</title>
          <attachments/>
        </step>
      </steps>
      <attachments>
        <attachment source="875b28a1a27b4636e82bd6c42889c144eea4b247bc3aca68e9c9d275396be853-attachment.png" title="Clique aqui para ver o print da tela" size="4990" type="image/png"/>
      </attachments>
      <labels>
        <label name="severity" value="normal"/>
        <label name="thread" value="21750940"/>
        <label name="host" value="DESKTOP-PVI2LJO"/>
        <label name="feature" value="Registro Imigrante"/>
        <label name="story" value="Gerar Requerimento de Registro do Imigrante para situacao em Suspenso"/>
      </labels>
      <parameters/>
    </test-case>
    <test-case start="1566839748993" stop="1566839750915" status="passed">
      <name>Verificar Protocolo de Registro do Imigrante em Suspenso na Internet</name>
      <title>Verificar Protocolo de Registro do Imigrante em Suspenso na Internet</title>
      <steps>
        <step start="1566839750042" stop="1566839750042" status="passed">
          <name>Quando realizar o procedimento de "Verificacao_de_Protocolo" de Imigrante na Internet</name>
          <title>Quando realizar o procedimento de "Verificacao_de_Protocolo" de Imigrante na Internet</title>
          <attachments/>
        </step>
        <step start="1566839750042" stop="1566839750631" status="passed">
          <name>E preencho os Dados de "Registro" do requerimento para "Verificacao_de_Protocolo" e clico em Verificar</name>
          <title>E preencho os Dados de "Registro" do requerimento para "Verificacao_de_Protocolo" e clico em Verificar</title>
          <attachments/>
        </step>
        <step start="1566839750631" stop="1566839750633" status="passed">
          <name>Entao eu visualizo a Verificacao do Protocolo referente</name>
          <title>Entao eu visualizo a Verificacao do Protocolo referente</title>
          <attachments/>
        </step>
      </steps>
      <attachments>
        <attachment source="6d8f5294c8703e5bd7622db7ad43c4eeb6d8d0321090af74a36141ed4886e83c-attachment.png" title="Clique aqui para ver o print da tela" size="19501" type="image/png"/>
      </attachments>
      <labels>
        <label name="severity" value="normal"/>
        <label name="thread" value="21750940"/>
        <label name="host" value="DESKTOP-PVI2LJO"/>
        <label name="feature" value="Registro Imigrante"/>
        <label name="story" value="Verificar Protocolo de Registro do Imigrante em Suspenso na Internet"/>
      </labels>
      <parameters/>
    </test-case>
    <test-case start="1566839750921" stop="1566839754275" status="passed">
      <name>Andamento do Requerimento de Registro do Imigrante em Suspenso na Internet</name>
      <title>Andamento do Requerimento de Registro do Imigrante em Suspenso na Internet</title>
      <steps>
        <step start="1566839752082" stop="1566839752082" status="passed">
          <name>Quando realizar o procedimento de "Andamento_do_Requerimento" de Imigrante na Internet</name>
          <title>Quando realizar o procedimento de "Andamento_do_Requerimento" de Imigrante na Internet</title>
          <attachments/>
        </step>
        <step start="1566839752083" stop="1566839754013" status="passed">
          <name>E preencho os Dados de "Registro" do requerimento para "Andamento_do_Requerimento" e clico em Pesquisar</name>
          <title>E preencho os Dados de "Registro" do requerimento para "Andamento_do_Requerimento" e clico em Pesquisar</title>
          <attachments/>
        </step>
        <step start="1566839754013" stop="1566839754014" status="passed">
          <name>Entao eu visualizo o andamento do requerimento "Suspenso"</name>
          <title>Entao eu visualizo o andamento do requerimento "Suspenso"</title>
          <attachments/>
        </step>
      </steps>
      <attachments>
        <attachment source="9ad59c6da521fd20084ac7bcef53edfcf7372f5d6b4b62605445c84c484c9f36-attachment.png" title="Clique aqui para ver o print da tela" size="60685" type="image/png"/>
      </attachments>
      <labels>
        <label name="severity" value="normal"/>
        <label name="thread" value="21750940"/>
        <label name="host" value="DESKTOP-PVI2LJO"/>
        <label name="feature" value="Registro Imigrante"/>
        <label name="story" value="Andamento do Requerimento de Registro do Imigrante em Suspenso na Internet"/>
      </labels>
      <parameters/>
    </test-case>
    <test-case start="1566839754279" stop="1566839823979" status="passed">
      <name>Alterar Tipos de Solicitacoes de Registro do Imigrante em Suspenso na Intranet</name>
      <title>Alterar Tipos de Solicitacoes de Registro do Imigrante em Suspenso na Intranet</title>
      <steps>
        <step start="1566839760872" stop="1566839760872" status="passed">
          <name>Quando processar atendimento de "Registro" no menu "Processar_Atendimento" na Intranet</name>
          <title>Quando processar atendimento de "Registro" no menu "Processar_Atendimento" na Intranet</title>
          <attachments/>
        </step>
        <step start="1566839760872" stop="1566839764786" status="passed">
          <name>E preencher as informacoes para Pesquisar Solicitacao de "Registro" na Situacao "Suspenso"</name>
          <title>E preencher as informacoes para Pesquisar Solicitacao de "Registro" na Situacao "Suspenso"</title>
          <attachments/>
        </step>
        <step start="1566839764786" stop="1566839823581" status="passed">
          <name>E clico para Alterar o Tipo de Solicitacao de "Registro"</name>
          <title>E clico para Alterar o Tipo de Solicitacao de "Registro"</title>
          <attachments/>
        </step>
      </steps>
      <attachments>
        <attachment source="875b28a1a27b4636e82bd6c42889c144eea4b247bc3aca68e9c9d275396be853-attachment.png" title="Clique aqui para ver o print da tela" size="4990" type="image/png"/>
      </attachments>
      <labels>
        <label name="severity" value="normal"/>
        <label name="thread" value="21750940"/>
        <label name="host" value="DESKTOP-PVI2LJO"/>
        <label name="feature" value="Registro Imigrante"/>
        <label name="story" value="Alterar Tipos de Solicitacoes de Registro do Imigrante em Suspenso na Intranet"/>
      </labels>
      <parameters/>
    </test-case>
    <test-case start="1566839823984" stop="1566839832429" status="passed">
      <name>Situacao do Requerimento de Registro do Imigrante em Suspenso na Intranet</name>
      <title>Situacao do Requerimento de Registro do Imigrante em Suspenso na Intranet</title>
      <steps>
        <step start="1566839830329" stop="1566839830329" status="passed">
          <name>Quando solicitar Situacao do Requerimento de "Registro" no menu "Situacao_do_Requerimento" na Intranet</name>
          <title>Quando solicitar Situacao do Requerimento de "Registro" no menu "Situacao_do_Requerimento" na Intranet</title>
          <attachments/>
        </step>
        <step start="1566839830329" stop="1566839832126" status="passed">
          <name>E preencho o numero do Requerimento para verificar a Situacao do Requerimento</name>
          <title>E preencho o numero do Requerimento para verificar a Situacao do Requerimento</title>
          <attachments/>
        </step>
        <step start="1566839832126" stop="1566839832127" status="passed">
          <name>Entao eu visualizo a situacao do Requerimento "Suspenso"</name>
          <title>Entao eu visualizo a situacao do Requerimento "Suspenso"</title>
          <attachments/>
        </step>
      </steps>
      <attachments>
        <attachment source="69082c1bd4ce208fdbc746a8b90f31a8f58dfc6dd0ac9a0f7aa7064885791f34-attachment.png" title="Clique aqui para ver o print da tela" size="69450" type="image/png"/>
      </attachments>
      <labels>
        <label name="severity" value="normal"/>
        <label name="thread" value="21750940"/>
        <label name="host" value="DESKTOP-PVI2LJO"/>
        <label name="feature" value="Registro Imigrante"/>
        <label name="story" value="Situacao do Requerimento de Registro do Imigrante em Suspenso na Intranet"/>
      </labels>
      <parameters/>
    </test-case>
    <test-case start="1566839832433" stop="1566839890950" status="passed">
      <name>Processar Atendimento de Registro do Imigrante em Suspenso na Intranet</name>
      <title>Processar Atendimento de Registro do Imigrante em Suspenso na Intranet</title>
      <steps>
        <step start="1566839839097" stop="1566839839097" status="passed">
          <name>Quando processar atendimento de "Registro" no menu "Processar_Atendimento" na Intranet</name>
          <title>Quando processar atendimento de "Registro" no menu "Processar_Atendimento" na Intranet</title>
          <attachments/>
        </step>
        <step start="1566839839097" stop="1566839842763" status="passed">
          <name>E preencher as informacoes para Pesquisar Solicitacao de "Registro" na Situacao "Suspenso"</name>
          <title>E preencher as informacoes para Pesquisar Solicitacao de "Registro" na Situacao "Suspenso"</title>
          <attachments/>
        </step>
        <step start="1566839842763" stop="1566839857199" status="passed">
          <name>E preencho Dados Pessoais e clico em Proximo</name>
          <title>E preencho Dados Pessoais e clico em Proximo</title>
          <attachments/>
        </step>
        <step start="1566839857199" stop="1566839862878" status="passed">
          <name>E preencho Dados do Registro e clico em Proximo</name>
          <title>E preencho Dados do Registro e clico em Proximo</title>
          <attachments/>
        </step>
        <step start="1566839862878" stop="1566839867265" status="passed">
          <name>E preencho Dados do Endereco e clico em Proximo</name>
          <title>E preencho Dados do Endereco e clico em Proximo</title>
          <attachments/>
        </step>
        <step start="1566839867265" stop="1566839878490" status="passed">
          <name>E preencho Dados de Documentos e clico em Proximo</name>
          <title>E preencho Dados de Documentos e clico em Proximo</title>
          <attachments/>
        </step>
        <step start="1566839878490" stop="1566839884524" status="passed">
          <name>E preencho Dados do Resultado da Pesquisa e clico em Proximo</name>
          <title>E preencho Dados do Resultado da Pesquisa e clico em Proximo</title>
          <attachments/>
        </step>
        <step start="1566839884524" stop="1566839890598" status="passed">
          <name>E visualizo Dados da Previa da Carteira e clico em "Concluir"</name>
          <title>E visualizo Dados da Previa da Carteira e clico em "Concluir"</title>
          <attachments/>
        </step>
        <step start="1566839890598" stop="1566839890600" status="passed">
          <name>Entao verifico o requerimento referente "Em Processamento"</name>
          <title>Entao verifico o requerimento referente "Em Processamento"</title>
          <attachments/>
        </step>
      </steps>
      <attachments>
        <attachment source="be21ca6a4482cf26b4e9d8259c9199aff170b0c8f2f76f16c116d18982015a82-attachment.png" title="Clique aqui para ver o print da tela" size="55960" type="image/png"/>
      </attachments>
      <labels>
        <label name="severity" value="normal"/>
        <label name="thread" value="21750940"/>
        <label name="host" value="DESKTOP-PVI2LJO"/>
        <label name="feature" value="Registro Imigrante"/>
        <label name="story" value="Processar Atendimento de Registro do Imigrante em Suspenso na Intranet"/>
      </labels>
      <parameters/>
    </test-case>
    <test-case start="1566839890954" stop="1566839899514" status="passed">
      <name>Situacao do Requerimento de Registro do Imigrante que estava em suspenso em Processamento na Intranet</name>
      <title>Situacao do Requerimento de Registro do Imigrante que estava em suspenso em Processamento na Intranet</title>
      <steps>
        <step start="1566839897340" stop="1566839897341" status="passed">
          <name>Quando solicitar Situacao do Requerimento de "Registro" no menu "Situacao_do_Requerimento" na Intranet</name>
          <title>Quando solicitar Situacao do Requerimento de "Registro" no menu "Situacao_do_Requerimento" na Intranet</title>
          <attachments/>
        </step>
        <step start="1566839897341" stop="1566839899207" status="passed">
          <name>E preencho o numero do Requerimento para verificar a Situacao do Requerimento</name>
          <title>E preencho o numero do Requerimento para verificar a Situacao do Requerimento</title>
          <attachments/>
        </step>
        <step start="1566839899207" stop="1566839899209" status="passed">
          <name>Entao eu visualizo a situacao do Requerimento "Em Processamento"</name>
          <title>Entao eu visualizo a situacao do Requerimento "Em Processamento"</title>
          <attachments/>
        </step>
      </steps>
      <attachments>
        <attachment source="af33a4719369f407751dfd09109b054311d9137997d49394dbbd9892248b3758-attachment.png" title="Clique aqui para ver o print da tela" size="69435" type="image/png"/>
      </attachments>
      <labels>
        <label name="severity" value="normal"/>
        <label name="thread" value="21750940"/>
        <label name="host" value="DESKTOP-PVI2LJO"/>
        <label name="feature" value="Registro Imigrante"/>
        <label name="story" value="Situacao do Requerimento de Registro do Imigrante que estava em suspenso em Processamento na Intranet"/>
      </labels>
      <parameters/>
    </test-case>
  </test-cases>
  <labels>
    <label name="severity" value="normal"/>
    <label name="thread" value="21750940"/>
    <label name="host" value="DESKTOP-PVI2LJO"/>
  </labels>
</ns2:test-suite>
